iq_core/__init__.py
iq_core/anotations/__init__.py
iq_core/anotations/connection.py
iq_core/anotations/time.py
iq_core/entities/__init__.py
iq_core/entities/account.py
iq_core/entities/candle.py
iq_core/entities/candle_stream.py
iq_core/entities/duration.py
iq_core/entities/instrument.py
iq_core/entities/message.py
iq_core/entities/profile.py
iq_core/entities/signal.py
iq_core/entities/trade_result.py
iq_core/exceptions/__init__.py
iq_core/exceptions/authentication_error.py
iq_core/exceptions/connection_error.py
iq_core/exceptions/iqoption_error.py
iq_core/exceptions/time_error.py
iq_core/exceptions/trading_error.py
iq_core/exceptions/validation_error.py
iq_core/services/__init__.py
iq_core/services/account_service.py
iq_core/services/auth_service.py
iq_core/services/binary_trade_service.py
iq_core/services/blitz_trade_service.py
iq_core/services/candle_service.py
iq_core/services/cotation_service.py
iq_core/services/digital_trade_service.py
iq_core/services/forex_trade_service.py
iq_core/services/instrument_resolver.py
iq_core/services/instrument_service.py
iq_core/services/token_service.py
iq_core/services/trade_mood_service.py
iq_core/services/trading_manager_service.py
iq_core/services/interfaces/__init__.py
iq_core/services/interfaces/trading_service.py
iq_core/websocket/__init__.py
iq_core/websocket/client.py
iq_core-1.0.11.dist-info/METADATA
iq_core-1.0.11.dist-info/WHEEL
iq_core-1.0.11.dist-info/top_level.txt
iq_core-1.0.11.dist-info/RECORD
