Metadata-Version: 2.4
Name: iq-core
Version: 1.0.11
Summary: API wrapper para IQ Option
Author-email: Célio Junior <profissional.celiojunior@outlook.com>
License-Expression: MIT
Project-URL: Homepage, https://github.com/celiovmjr/iq-core
Project-URL: Source, https://github.com/celiovmjr/iq-core
Project-URL: Issues, https://github.com/celiovmjr/iq-core/issues
Classifier: Development Status :: 5 - Production/Stable
Classifier: Intended Audience :: Developers
Classifier: Programming Language :: Python :: 3
Classifier: Programming Language :: Python :: 3.10
Classifier: Programming Language :: Python :: 3.11
Classifier: Programming Language :: Python :: 3.12
Classifier: Programming Language :: Python :: 3.13
Classifier: Operating System :: OS Independent
Requires-Python: >=3.10
Requires-Dist: aiohttp>=3.12.0
Requires-Dist: websockets>=15.0.0
Requires-Dist: cryptography>=45.0.0
